hyperbolic3d/__init__.py
hyperbolic3d/gyro.py
pyhyperbolic3d-0.1.0.dist-info/LICENSE
pyhyperbolic3d-0.1.0.dist-info/WHEEL
pyhyperbolic3d-0.1.0.dist-info/METADATA
pyhyperbolic3d-0.1.0.dist-info/RECORD
