Metadata-Version: 2.1
Name: pyhyperbolic3d
Version: 0.1.0
Summary: Hyperbolic meshes for 'PyVista'
Home-page: https://github.com/stla/PyHyperbolic3D
License: GPL-3.0-only
Keywords: hyperbolic geometry,3D meshes,PyVista
Author: Stéphane Laurent
Author-email: laurent_step@outook.fr
Requires-Python: >=3.9,<3.11
Classifier: License :: OSI Approved :: GNU General Public License v3 (GPLv3)
Classifier: Programming Language :: Python :: 3
Classifier: Programming Language :: Python :: 3.9
Classifier: Programming Language :: Python :: 3.10
Provides-Extra: docs
Requires-Dist: numpy (>=1.21.2,<2.0.0)
Requires-Dist: pyvista (>=0.32.1,<0.33.0)
Requires-Dist: sphinx (>=5.3.0,<6.0.0); extra == "docs"
Requires-Dist: sphinx-rtd-theme (>=1.1.1,<2.0.0); extra == "docs"
Requires-Dist: sphinxcontrib-napoleon (>=0.7,<0.8); extra == "docs"
Requires-Dist: sphinxcontrib-restbuilder (>=0.3,<0.4); extra == "docs"
Project-URL: Documentation, https://pyhyperbolic3d.readthedocs.io/en/latest/
